smst/__init__.py
smst/models/__init__.py
smst/models/dft.py
smst/models/harmonic.py
smst/models/hpr.py
smst/models/hps.py
smst/models/sine.py
smst/models/spr.py
smst/models/sps.py
smst/models/stft.py
smst/models/stochastic.py
smst/ui/__init__.py
smst/ui/notebook.py
smst/ui/models/__init__.py
smst/ui/models/dftModel_GUI_frame.py
smst/ui/models/dftModel_function.py
smst/ui/models/harmonicModel_GUI_frame.py
smst/ui/models/harmonicModel_function.py
smst/ui/models/hprModel_GUI_frame.py
smst/ui/models/hprModel_function.py
smst/ui/models/hpsModel_GUI_frame.py
smst/ui/models/hpsModel_function.py
smst/ui/models/models_GUI.py
smst/ui/models/sineModel_GUI_frame.py
smst/ui/models/sineModel_function.py
smst/ui/models/sprModel_GUI_frame.py
smst/ui/models/sprModel_function.py
smst/ui/models/spsModel_GUI_frame.py
smst/ui/models/spsModel_function.py
smst/ui/models/stftModel_GUI_frame.py
smst/ui/models/stftModel_function.py
smst/ui/models/stochasticModel_GUI_frame.py
smst/ui/models/stochasticModel_function.py
smst/ui/transformations/__init__.py
smst/ui/transformations/harmonicTransformations_GUI_frame.py
smst/ui/transformations/harmonicTransformations_function.py
smst/ui/transformations/hpsMorph_GUI_frame.py
smst/ui/transformations/hpsMorph_function.py
smst/ui/transformations/hpsTransformations_GUI_frame.py
smst/ui/transformations/hpsTransformations_function.py
smst/ui/transformations/sineTransformations_GUI_frame.py
smst/ui/transformations/sineTransformations_function.py
smst/ui/transformations/stftMorph_GUI_frame.py
smst/ui/transformations/stftMorph_function.py
smst/ui/transformations/stochasticTransformations_GUI_frame.py
smst/ui/transformations/stochasticTransformations_function.py
smst/ui/transformations/transformations_GUI.py
smst/utils/__init__.py
smst/utils/audio.py
smst/utils/files.py
smst/utils/math.py
smst/utils/peaks.py
smst/utils/residual.py
smst/utils/synth.py
smst/utils/window.py
smst-0.3.1.dist-info/DESCRIPTION.rst
smst-0.3.1.dist-info/METADATA
smst-0.3.1.dist-info/RECORD
smst-0.3.1.dist-info/WHEEL
smst-0.3.1.dist-info/entry_points.txt
smst-0.3.1.dist-info/metadata.json
smst-0.3.1.dist-info/top_level.txt
