Metadata-Version: 2.0
Name: smst
Version: 0.3.1
Summary: SMS tools - spectral audio modeling/synthesis/transformations
Home-page: https://github.com/MTG/sms-tools
Author: Xavier Serra, Fabia Serra Arrizabalaga, Sankalp Gulati and others
Author-email: xavier.serra@upf.edu
License: AGPL
Keywords: audio spectral modelling analysis synthesis
Platform: UNKNOWN
Classifier: Development Status :: 3 - Alpha
Classifier: Intended Audience :: Developers
Classifier: Intended Audience :: Education
Classifier: Intended Audience :: Science/Research
Classifier: Topic :: Multimedia :: Sound/Audio :: Analysis
Classifier: Topic :: Multimedia :: Sound/Audio :: Sound Synthesis
Classifier: License :: OSI Approved :: GNU Affero General Public License v3 or later (AGPLv3+)
Classifier: Programming Language :: Python :: 2
Classifier: Programming Language :: Python :: 2.7
Classifier: Operating System :: POSIX :: Linux
Classifier: Operating System :: MacOS :: MacOS X
Requires-Dist: cython
Requires-Dist: matplotlib
Requires-Dist: numpy
Requires-Dist: scipy
